<?xml version="1.0" encoding="UTF-8"?>
<objects serializationModel="Studio.02.02.00">
	<object class="AudioFile" id="{95052014-e134-4775-8dfc-4f3871ad0ba1}">
		<property name="assetPath">
			<value>fsStone_3.wav</value>
		</property>
		<property name="frequencyInKHz">
			<value>48</value>
		</property>
		<property name="channelCount">
			<value>2</value>
		</property>
		<property name="length">
			<value>0.42325000000000002</value>
		</property>
		<relationship name="masterAssetFolder">
			<destination>{38cc5cfc-ede5-4794-806d-293c61a942cc}</destination>
		</relationship>
	</object>
</objects>
